HemantDhanwar/EmailServices.py
HemantDhanwar/__init__.py
HemantDhanwar-0.1.2.dist-info/LICENCE.txt
HemantDhanwar-0.1.2.dist-info/METADATA
HemantDhanwar-0.1.2.dist-info/WHEEL
HemantDhanwar-0.1.2.dist-info/top_level.txt
HemantDhanwar-0.1.2.dist-info/RECORD
